betterpythonchallenge/__module__.py
betterpythonchallenge/extract_and_transform_match.py
betterpythonchallenge/extract_and_transform_source.py
betterpythonchallenge/matcher.py
betterpythonchallenge-0.1.dist-info/DESCRIPTION.rst
betterpythonchallenge-0.1.dist-info/METADATA
betterpythonchallenge-0.1.dist-info/RECORD
betterpythonchallenge-0.1.dist-info/WHEEL
betterpythonchallenge-0.1.dist-info/metadata.json
betterpythonchallenge-0.1.dist-info/top_level.txt
